whitebox_plugin_telegraf/pyproject.toml
whitebox_plugin_telegraf/__init__.py
whitebox_plugin_telegraf/apps.py
whitebox_plugin_telegraf/migrations/0001_initial.py
whitebox_plugin_telegraf/migrations/__init__.py
whitebox_plugin_telegraf/models.py
whitebox_plugin_telegraf/whitebox_plugin_telegraf.py
whitebox_plugin_telegraf-0.1.1.dist-info/LICENSE
whitebox_plugin_telegraf-0.1.1.dist-info/METADATA
whitebox_plugin_telegraf-0.1.1.dist-info/WHEEL
whitebox_plugin_telegraf-0.1.1.dist-info/entry_points.txt
whitebox_plugin_telegraf-0.1.1.dist-info/RECORD
